pylutron_caseta/__init__.py
pylutron_caseta/assets.py
pylutron_caseta/cli.py
pylutron_caseta/color_value.py
pylutron_caseta/leap.py
pylutron_caseta/messages.py
pylutron_caseta/pairing.py
pylutron_caseta/smartbridge.py
pylutron_caseta/utils.py
pylutron_caseta-0.26.0.dist-info/METADATA
pylutron_caseta-0.26.0.dist-info/WHEEL
pylutron_caseta-0.26.0.dist-info/entry_points.txt
pylutron_caseta-0.26.0.dist-info/licenses/LICENSE
pylutron_caseta-0.26.0.dist-info/RECORD
