Metadata-Version: 2.4
Name: pylutron-caseta
Version: 0.26.0
Summary: Provides an API to the Lutron Smartbridge
Project-URL: Homepage, https://github.com/gurumitts/pylutron-caseta
Author: gurumitts
Maintainer: mdonoughe
License-Expression: Apache-2.0
License-File: LICENSE
Classifier: License :: OSI Approved :: Apache Software License
Requires-Python: >=3.9.0
Requires-Dist: async-timeout>=3.0.1; python_version < '3.11'
Requires-Dist: cryptography
Requires-Dist: orjson
Provides-Extra: cli
Requires-Dist: click~=8.1.2; extra == 'cli'
Requires-Dist: xdg~=5.1.1; extra == 'cli'
Requires-Dist: zeroconf~=0.38.4; extra == 'cli'
